khoj/__init__.py
khoj/configure.py
khoj/main.py
khoj/manage.py
khoj/app/README.md
khoj/app/__init__.py
khoj/app/asgi.py
khoj/app/settings.py
khoj/app/urls.py
khoj/database/__init__.py
khoj/database/admin.py
khoj/database/apps.py
khoj/database/tests.py
khoj/database/adapters/__init__.py
khoj/database/management/__init__.py
khoj/database/management/commands/__init__.py
khoj/database/management/commands/change_default_model.py
khoj/database/management/commands/change_generated_images_url.py
khoj/database/management/commands/convert_images_png_to_webp.py
khoj/database/management/commands/delete_orphaned_fileobjects.py
khoj/database/migrations/0001_khojuser.py
khoj/database/migrations/0002_googleuser.py
khoj/database/migrations/0003_vector_extension.py
khoj/database/migrations/0004_content_types_and_more.py
khoj/database/migrations/0005_embeddings_corpus_id.py
khoj/database/migrations/0006_embeddingsdates.py
khoj/database/migrations/0007_add_conversation.py
khoj/database/migrations/0008_alter_conversation_conversation_log.py
khoj/database/migrations/0009_khojapiuser.py
khoj/database/migrations/0010_chatmodeloptions_and_more.py
khoj/database/migrations/0010_rename_embeddings_entry_and_more.py
khoj/database/migrations/0011_merge_20231102_0138.py
khoj/database/migrations/0012_entry_file_source.py
khoj/database/migrations/0013_subscription.py
khoj/database/migrations/0014_alter_googleuser_picture.py
khoj/database/migrations/0015_alter_subscription_user.py
khoj/database/migrations/0016_alter_subscription_renewal_date.py
khoj/database/migrations/0017_searchmodel.py
khoj/database/migrations/0018_searchmodelconfig_delete_searchmodel.py
khoj/database/migrations/0019_alter_googleuser_family_name_and_more.py
khoj/database/migrations/0020_reflectivequestion.py
khoj/database/migrations/0021_speechtotextmodeloptions_and_more.py
khoj/database/migrations/0022_texttoimagemodelconfig.py
khoj/database/migrations/0023_usersearchmodelconfig.py
khoj-1.42.10.dist-info/METADATA
khoj-1.42.10.dist-info/WHEEL
khoj-1.42.10.dist-info/entry_points.txt
khoj-1.42.10.dist-info/licenses/LICENSE
khoj-1.42.10.dist-info/RECORD
