Metadata-Version: 2.4
Name: khoj
Version: 1.42.10
Summary: Your Second Brain
Project-URL: Homepage, https://khoj.dev
Project-URL: Documentation, https://docs.khoj.dev
Project-URL: Code, https://github.com/khoj-ai/khoj
Author: Debanjum Singh Solanky, Saba Imran
License-Expression: AGPL-3.0-or-later
License-File: LICENSE
Keywords: AI,NLP,images,markdown,org-mode,pdf,productivity,search,semantic-search
Classifier: Development Status :: 5 - Production/Stable
Classifier: Intended Audience :: Information Technology
Classifier: License :: OSI Approved :: GNU Affero General Public License v3 or later (AGPLv3+)
Classifier: Operating System :: OS Independent
Classifier: Programming Language :: Python :: 3
Classifier: Programming Language :: Python :: 3.10
Classifier: Programming Language :: Python :: 3.11
Classifier: Programming Language :: Python :: 3.12
Classifier: Topic :: Internet :: WWW/HTTP :: Indexing/Search
Classifier: Topic :: Scientific/Engineering :: Artificial Intelligence
Classifier: Topic :: Scientific/Engineering :: Human Machine Interfaces
Requires-Python: <3.13,>=3.10
Requires-Dist: aiohttp~=3.9.0
Requires-Dist: anthropic==0.52.0
Requires-Dist: anyio~=4.8.0
Requires-Dist: apscheduler~=3.10.0
Requires-Dist: authlib==1.2.1
Requires-Dist: beautifulsoup4~=4.12.3
Requires-Dist: cron-descriptor==1.4.3
Requires-Dist: dateparser>=1.1.1
Requires-Dist: defusedxml==0.7.1
Requires-Dist: django-apscheduler==0.7.0
Requires-Dist: django-phonenumber-field==7.3.0
Requires-Dist: django-unfold==0.42.0
Requires-Dist: django==5.1.10
Requires-Dist: docx2txt==0.8
Requires-Dist: e2b-code-interpreter~=1.0.0
Requires-Dist: einops==0.8.0
Requires-Dist: email-validator==2.2.0
Requires-Dist: fastapi>=0.110.0
Requires-Dist: google-auth~=2.23.3
Requires-Dist: google-genai==1.11.0
Requires-Dist: httpx==0.28.1
Requires-Dist: huggingface-hub[hf-xet]>=0.22.2
Requires-Dist: itsdangerous==2.1.2
Requires-Dist: jinja2==3.1.6
Requires-Dist: langchain-community==0.3.3
Requires-Dist: langchain-text-splitters==0.3.1
Requires-Dist: llama-cpp-python==0.2.88
Requires-Dist: lxml==4.9.3
Requires-Dist: magika~=0.5.1
Requires-Dist: markdown-it-py~=3.0.0
Requires-Dist: markdownify~=0.11.6
Requires-Dist: openai-whisper>=20231117
Requires-Dist: openai>=1.86.0
Requires-Dist: pgvector==0.2.4
Requires-Dist: phonenumbers==8.13.27
Requires-Dist: pillow~=10.0.0
Requires-Dist: psutil>=5.8.0
Requires-Dist: psycopg2-binary==2.9.9
Requires-Dist: pydantic[email]>=2.0.0
Requires-Dist: pyjson5==1.6.7
Requires-Dist: pymupdf==1.24.11
Requires-Dist: python-multipart>=0.0.7
Requires-Dist: pytz~=2024.1
Requires-Dist: pyyaml~=6.0
Requires-Dist: rapidocr-onnxruntime==1.3.24
Requires-Dist: requests>=2.26.0
Requires-Dist: resend==1.0.1
Requires-Dist: rich>=13.3.1
Requires-Dist: schedule==1.1.0
Requires-Dist: sentence-transformers==3.4.1
Requires-Dist: tenacity>=9.0.0
Requires-Dist: tiktoken>=0.3.2
Requires-Dist: torch==2.6.0
Requires-Dist: transformers>=4.51.0
Requires-Dist: tzdata==2023.3
Requires-Dist: uvicorn==0.30.6
Requires-Dist: websockets==13.0
Provides-Extra: dev
Requires-Dist: black>=23.1.0; extra == 'dev'
Requires-Dist: boto3>=1.34.57; extra == 'dev'
Requires-Dist: datasets; extra == 'dev'
Requires-Dist: factory-boy>=3.2.1; extra == 'dev'
Requires-Dist: freezegun>=1.2.0; extra == 'dev'
Requires-Dist: gitpython~=3.1.43; extra == 'dev'
Requires-Dist: gunicorn==22.0.0; extra == 'dev'
Requires-Dist: mypy>=1.0.1; extra == 'dev'
Requires-Dist: pandas; extra == 'dev'
Requires-Dist: pgserver==0.1.4; extra == 'dev'
Requires-Dist: pre-commit>=3.0.4; extra == 'dev'
Requires-Dist: pytest-asyncio==0.21.1; extra == 'dev'
Requires-Dist: pytest-django==4.5.2; extra == 'dev'
Requires-Dist: pytest-xdist[psutil]; extra == 'dev'
Requires-Dist: pytest>=7.1.2; extra == 'dev'
Requires-Dist: stripe==7.3.0; extra == 'dev'
Requires-Dist: twilio==8.11; extra == 'dev'
Provides-Extra: local
Requires-Dist: pgserver==0.1.4; extra == 'local'
Provides-Extra: prod
Requires-Dist: boto3>=1.34.57; extra == 'prod'
Requires-Dist: gunicorn==22.0.0; extra == 'prod'
Requires-Dist: stripe==7.3.0; extra == 'prod'
Requires-Dist: twilio==8.11; extra == 'prod'
